reposcape/__init__.py
reposcape/analyzers/__init__.py
reposcape/analyzers/base.py
reposcape/analyzers/python_ast.py
reposcape/analyzers/python_astroid.py
reposcape/analyzers/python_cst.py
reposcape/analyzers/text.py
reposcape/constants.py
reposcape/functions.py
reposcape/importance/__init__.py
reposcape/importance/base.py
reposcape/importance/frequency.py
reposcape/importance/graph.py
reposcape/importance/pagerank.py
reposcape/importance/scoring.py
reposcape/mapper.py
reposcape/models/__init__.py
reposcape/models/nodes.py
reposcape/models/options.py
reposcape/py.typed
reposcape/serializers/__init__.py
reposcape/serializers/base.py
reposcape/serializers/compact.py
reposcape/serializers/markdown.py
reposcape/serializers/tree.py
reposcape/utils/__init__.py
reposcape/utils/tokens.py
reposcape-1.0.2.dist-info/WHEEL
reposcape-1.0.2.dist-info/METADATA
reposcape-1.0.2.dist-info/RECORD
