Metadata-Version: 2.3
Name: reposcape
Version: 1.0.2
Summary: Repository maps for LLMs
Keywords: 
Author: Philipp Temminghoff
Author-email: Philipp Temminghoff <philipptemminghoff@googlemail.com>
License: MIT License
Classifier: Development Status :: 4 - Beta
Classifier: Intended Audience :: Developers
Classifier: Operating System :: OS Independent
Classifier: Programming Language :: Python :: 3
Classifier: Programming Language :: Python :: 3 :: Only
Classifier: Programming Language :: Python :: 3.12
Classifier: Programming Language :: Python :: 3.13
Classifier: Programming Language :: Python :: 3.14
Classifier: Topic :: Documentation
Classifier: Topic :: Software Development
Classifier: Topic :: Utilities
Classifier: Typing :: Typed
Requires-Dist: rustworkx>=0.15.1
Requires-Dist: tiktoken>=0.8.0
Requires-Dist: universal-pathlib>=0.2.5
Requires-Dist: upathtools>=0.6.5
Requires-Python: >=3.13
Project-URL: Code coverage, https://app.codecov.io/gh/phil65/reposcape
Project-URL: Discussions, https://github.com/phil65/reposcape/discussions
Project-URL: Documentation, https://phil65.github.io/reposcape/
Project-URL: Issues, https://github.com/phil65/reposcape/issues
Project-URL: Source, https://github.com/phil65/reposcape
